{
	"configurations" : 
	[
		{
			"directories" : 
			[
				{
					"build" : ".",
					"minimumCMakeVersion" : 
					{
						"string" : "3.12.1"
					},
					"projectIndex" : 0,
					"source" : ".",
					"targetIndexes" : 
					[
						0
					]
				}
			],
			"name" : "Debug",
			"projects" : 
			[
				{
					"directoryIndexes" : 
					[
						0
					],
					"name" : "project",
					"targetIndexes" : 
					[
						0
					]
				}
			],
			"targets" : 
			[
				{
					"directoryIndex" : 0,
					"id" : "bin::@6890427a1f51a3e7e1df",
					"jsonFile" : "target-bin-Debug-6c9cea920f61a1ed3b73.json",
					"name" : "bin",
					"projectIndex" : 0
				}
			]
		}
	],
	"kind" : "codemodel",
	"paths" : 
	{
		"build" : "/home/alexandr/files/git_hub/operating-systems/2/build",
		"source" : "/home/alexandr/files/git_hub/operating-systems/2"
	},
	"version" : 
	{
		"major" : 2,
		"minor" : 0
	}
}
